.DS_Store
conf/logger.ini
src/aws_publish_raspberry_server.py
src/command_line.py
src/jsonconverter.py
src/log_util.py
src/publish_fake_date.py
src/repository_dynamo.py
src/flaskapp/__init__.py
src/flaskapp/forms.py
src/flaskapp/routes.py
src/flaskapp/static/.DS_Store
src/flaskapp/static/css/animate.min.css
src/flaskapp/static/css/bootstrap.min.css
src/flaskapp/static/css/main.css
src/flaskapp/static/css/paper-dashboard.css
src/flaskapp/static/css/themify-icons.css
src/flaskapp/static/fonts/themify.eot
src/flaskapp/static/fonts/themify.svg
src/flaskapp/static/fonts/themify.ttf
src/flaskapp/static/fonts/themify.woff
src/flaskapp/static/img/aws.png
src/flaskapp/static/img/logo.png
src/flaskapp/static/js/bootstrap-checkbox-radio.js
src/flaskapp/static/js/bootstrap.min.js
src/flaskapp/static/js/chartist.min.js
src/flaskapp/static/js/jquery.min.js
src/flaskapp/static/js/main.js
src/flaskapp/static/js/paper-dashboard.js
src/flaskapp/templates/dashboard.html
src/flaskapp/templates/graph.html
src/flaskapp/templates/login.html
src/flaskapp/templates/navbar.html
src/flaskapp/templates/setting.html
src/flaskapp/templates/template.html
SmartGarden-1.0.1.dist-info/LICENSE
SmartGarden-1.0.1.dist-info/METADATA
SmartGarden-1.0.1.dist-info/WHEEL
SmartGarden-1.0.1.dist-info/entry_points.txt
SmartGarden-1.0.1.dist-info/top_level.txt
SmartGarden-1.0.1.dist-info/RECORD
